LICENSE
MANIFEST.in
README.rst
setup.py
wagtail_podcast/.directory
wagtail_podcast/__init__.py
wagtail_podcast/admin.py
wagtail_podcast/apps.py
wagtail_podcast/models.py
wagtail_podcast/tests.py
wagtail_podcast/views.py
wagtail_podcast.egg-info/PKG-INFO
wagtail_podcast.egg-info/SOURCES.txt
wagtail_podcast.egg-info/dependency_links.txt
wagtail_podcast.egg-info/requires.txt
wagtail_podcast.egg-info/top_level.txt
wagtail_podcast/__pycache__/__init__.cpython-36.pyc
wagtail_podcast/__pycache__/admin.cpython-36.pyc
wagtail_podcast/__pycache__/models.cpython-36.pyc
wagtail_podcast/docs/Makefile
wagtail_podcast/docs/source/api.rst
wagtail_podcast/docs/source/changelog.rst
wagtail_podcast/docs/source/conf.py
wagtail_podcast/docs/source/customising.rst
wagtail_podcast/docs/source/getting-started.rst
wagtail_podcast/docs/source/index.rst
wagtail_podcast/docs/source/internationalisation.rst
wagtail_podcast/docs/source/podcast-options.rst
wagtail_podcast/docs/source/requirements.txt
wagtail_podcast/docs/source/roadmap.rst
wagtail_podcast/locale/af/LC_MESSAGES/django.mo
wagtail_podcast/locale/af/LC_MESSAGES/django.po
wagtail_podcast/migrations/0001_initial.py
wagtail_podcast/migrations/__init__.py
wagtail_podcast/migrations/__pycache__/0001_initial.cpython-36.pyc
wagtail_podcast/migrations/__pycache__/__init__.cpython-36.pyc
wagtail_podcast/static/wagtail_podcast/css/all.css
wagtail_podcast/static/wagtail_podcast/css/bootstrap.min.css
wagtail_podcast/static/wagtail_podcast/css/custom.css
wagtail_podcast/static/wagtail_podcast/css/mediaelementplayer.css
wagtail_podcast/static/wagtail_podcast/css/mejs-controls.png
wagtail_podcast/static/wagtail_podcast/css/mejs-controls.svg
wagtail_podcast/static/wagtail_podcast/images/blubrry.png
wagtail_podcast/static/wagtail_podcast/images/close.png
wagtail_podcast/static/wagtail_podcast/images/loading.gif
wagtail_podcast/static/wagtail_podcast/images/next.png
wagtail_podcast/static/wagtail_podcast/images/prev.png
wagtail_podcast/static/wagtail_podcast/js/bootstrap.bundle.min.js
wagtail_podcast/static/wagtail_podcast/js/jquery.min.js
wagtail_podcast/static/wagtail_podcast/js/mediaelement-and-player.min.js
