Metadata-Version: 2.1
Name: wagtail-podcast
Version: 0.1
Summary: A simple podcast app built for Wagtail CMS and Django
Home-page: https://gitlab.com/dfmeyer/wagtail_podcast
Author: Daniel F. Meyer
Author-email: me3064@gmail.com
License: MIT
Project-URL: Bug Tracker, https://gitlab.com/dfmeyer/wagtail_podcast/issues
Project-URL: Documentation, https://wagtail-podcast.readthedocs.io/en/latest/
Project-URL: Source Code, https://gitlab.com/dfmeyer/wagtail_podcast
Keywords: Django,Wagtail,podcast
Platform: UNKNOWN
Requires-Python: >=3.5
